multigenai/__init__.py
multigenai/multigenai.py
multigenai-1.0.0.dist-info/METADATA
multigenai-1.0.0.dist-info/WHEEL
multigenai-1.0.0.dist-info/top_level.txt
multigenai-1.0.0.dist-info/RECORD
